Workbook

Sheet Risk Register
A1: Risk ID | B1: Description | C1: Category | D1: Likelihood (1-5) | E1: Impact (1-5) | F1: Inherent score | G1: Rating | H1: NIST function | I1: NIST AI RMF ref | J1: ISO/IEC 42001 ref | K1: OWASP ref | L1: UK principle | M1: Basis / evidence | N1: Scoring rationale
A2: R01 | B2: Real errors missed on data unlike the planted patterns (false negatives) | C2: Accuracy / performance | D2: 4 | E2: 4 | F2: =D2*E2 | G2: =IF(F2>=Scoring!$B$11,"High",IF(F2>=Scoring!$B$12,"Medium","Low")) | H2: Measure | I2: MEASURE 2.3, 2.5 | J2: A.6 (life cycle: verification and validation) | K2: n/a | L2: Safety, security, robustness | M2: SysDesc s9: validation used patterns written to fit the rules; no unseen-data test | N2: Likely: rules are narrow and fixed. High impact: a missed duplicate or break is the main cost.
A3: R02 | B3: Clean items wrongly flagged (false positives) create review burden and desensitise reviewers | C3: Accuracy / performance | D3: 4 | E3: 3 | F3: =D3*E3 | G3: =IF(F3>=Scoring!$B$11,"High",IF(F3>=Scoring!$B$12,"Medium","Low")) | H3: Measure | I3: MEASURE 2.3 | J3: A.6 (verification and validation) | K3: n/a | L3: Safety, security, robustness | M3: Precision 0.70 (Xero), 0.778 (synthetic); 24 FPs on 5,000 lines | N3: Already observed at below the 0.80 criterion. Moderate impact: cost is time, not misstatement.
A4: R03 | B4: Reported accuracy is overstated because validation was circular (planted anomalies designed to fit the rules) | C4: Accuracy / performance | D4: 5 | E4: 4 | F4: =D4*E4 | G4: =IF(F4>=Scoring!$B$11,"High",IF(F4>=Scoring!$B$12,"Medium","Low")) | H4: Measure | I4: MEASURE 2.1, 2.3 | J4: A.6 (verification and validation) | K4: n/a | L4: Appropriate transparency and explainability | M4: README states planted patterns were written to fit the rules; Xero A2 tuned to per-contact VAT | N4: Certain as designed. High impact: a reader could rely on 7/7 as evidence of general accuracy.
A5: R04 | B5: Duplicate supplier bills not detected: A1 checks sales invoices (ACCREC) only | C5: Accuracy / performance | D5: 3 | E5: 4 | F5: =D5*E5 | G5: =IF(F5>=Scoring!$B$11,"High",IF(F5>=Scoring!$B$12,"Medium","Low")) | H5: Measure | I5: MEASURE 2.3 | J5: A.6 (verification and validation) | K5: n/a | L5: Safety, security, robustness | M5: rules.py:35-58 (ACCREC filter); to be confirmed in Phase 4 | N5: Possible gap pending test. Duplicate payables is a core reconciliation risk, so impact is high.
A6: R05 | B6: A1 compares adjacent sorted rows only, so three or more near-identical entries may be under-reported | C6: Accuracy / performance | D6: 2 | E6: 3 | F6: =D6*E6 | G6: =IF(F6>=Scoring!$B$11,"High",IF(F6>=Scoring!$B$12,"Medium","Low")) | H6: Measure | I6: MEASURE 2.3 | J6: A.6 (verification and validation) | K6: n/a | L6: Safety, security, robustness | M6: rules.py:35-58; to be confirmed in Phase 4 | N6: Uncommon pattern, and the pair is still flagged. Impact limited.
A7: R06 | B7: Fixed thresholds and tolerances (A3 £500, match tolerances, windows) are uncalibrated, unapproved and easy to avoid | C7: Accuracy / performance | D7: 3 | E7: 3 | F7: =D7*E7 | G7: =IF(F7>=Scoring!$B$11,"High",IF(F7>=Scoring!$B$12,"Medium","Low")) | H7: Map | I7: MAP 2.3, MAP 1.6 | J7: A.6 (design and development) | K7: n/a | L7: Safety, security, robustness | M7: matcher.py:17-20; rules.py:119; constants in code, no approval record | N7: Fixed constants can be gamed by a small change in amount or date.
A8: R07 | B8: Statistical outlier check (A7) is unreliable on small or uniform account populations | C8: Accuracy / performance | D8: 3 | E8: 3 | F8: =D8*E8 | G8: =IF(F8>=Scoring!$B$11,"High",IF(F8>=Scoring!$B$12,"Medium","Low")) | H8: Measure | I8: MEASURE 2.5 | J8: A.6 (verification and validation) | K8: n/a | L8: Safety, security, robustness | M8: statistical.py:43-60 (MAD-based; MAD=0 branch); live sample tiny | N8: Median/MAD degrades with few points. Moderate impact.
A9: R08 | B9: Reconciliation attributes bank lines to the wrong document, loses genuine matches or gives different results depending on record order (first match taken, no one-to-one allocation) | C9: Accuracy / performance | D9: 4 | E9: 4 | F9: =D9*E9 | G9: =IF(F9>=Scoring!$B$11,"High",IF(F9>=Scoring!$B$12,"Medium","Low")) | H9: Measure | I9: MEASURE 2.3 | J9: A.6 (verification and validation) | K9: n/a | L9: Safety, security, robustness | M9: Order dependence demonstrated (Phase 4, E-06); recurring receipt misattribution (E-02); QuickBooks 0/40 explained by sandbox data, not proven a matcher failure | N9: Demonstrated: reordering rows lost a true duplicate payment and created false ones. Impact raised to 4 (a missed duplicate payment).
A10: R09 | B10: Weekend-posting rule (A4) produces false positives on legitimate items and ignores public holidays | C10: Accuracy / performance | D10: 3 | E10: 2 | F10: =D10*E10 | G10: =IF(F10>=Scoring!$B$11,"High",IF(F10>=Scoring!$B$12,"Medium","Low")) | H10: Measure | I10: MEASURE 2.3 | J10: A.6 (verification and validation) | K10: n/a | L10: Safety, security, robustness | M10: rules.py:146-160 (weekday test) | N10: Low value signal but low harm.
A11: R10 | B11: Variance explanations name drivers that move against the headline, cannot name contacts that disappeared, and read as causal explanations | C11: Explainability / transparency | D11: 4 | E11: 3 | F11: =D11*E11 | G11: =IF(F11>=Scoring!$B$11,"High",IF(F11>=Scoring!$B$12,"Medium","Low")) | H11: Measure | I11: MEASURE 2.8 | J11: A.8 (information for interested parties) | K11: n/a | L11: Appropriate transparency and explainability | M11: 17 of 52 test sentences and 35 of 69 on Northbridge's synthetic data name an opposing driver (E-05); explainer.py:88-93 | N11: Demonstrated defect in templated text (not hallucination); likelihood raised to 4.
A12: R11 | B12: Unpinned dependencies allow silent behaviour change across installs or redeploys | C12: Consistency / determinism | D12: 3 | E12: 3 | F12: =D12*E12 | G12: =IF(F12>=Scoring!$B$11,"High",IF(F12>=Scoring!$B$12,"Medium","Low")) | H12: Manage | I12: MANAGE 2.3 | J12: A.6 (life cycle: change) | K12: n/a | L12: Safety, security, robustness | M12: requirements.txt unpinned; no lockfile | N12: Streamlit Cloud rebuilds from unpinned requirements; effect on output unknown.
A13: R12 | B13: Incomplete or malformed ledger data (missing contacts, voided invoices, unlinked payments) yields confident but wrong results | C13: Data quality | D13: 3 | E13: 4 | F13: =D13*E13 | G13: =IF(F13>=Scoring!$B$11,"High",IF(F13>=Scoring!$B$12,"Medium","Low")) | H13: Map | I13: MAP 2.3 | J13: A.7 (data for AI systems) | K13: n/a | L13: Safety, security, robustness | M13: Coverage table shows unlinked payments, no-contact bank lines | N13: Real ledgers are messy; no input validation gate found.
... A29: R28 | B29: Reviewer is also the developer, and code was built with AI coding tools, weakening independence and provenance assurance | C29: Governance | D29: 5 | E29: 2 | F29: =D29*E29 | G29: =IF(F29>=Scoring!$B$11,"High",IF(F29>=Scoring!$B$12,"Medium","Low")) | H29: Govern | I29: GOVERN 4.1 | J29: A.3 (organisation); A.6 | K29: n/a | L29: Accountability and governance | M29: ToR s1 (independence disclosure) | N29: Certain; disclosed and partly mitigated by a challenge review.

Sheet Summary
A1: Risk register summary
A3: Category | B3: Risks | C3: High | D3: Medium | E3: Low
A4: Accuracy / performance | B4: =COUNTIF('Risk Register'!$C$2:$C$29,A4) | C4: =COUNTIFS('Risk Register'!$C$2:$C$29,$A4,'Risk Register'!$G$2:$G$29,"High") | D4: =COUNTIFS('Risk Register'!$C$2:$C$29,$A4,'Risk Register'!$G$2:$G$29,"Medium") | E4: =COUNTIFS('Risk Register'!$C$2:$C$29,$A4,'Risk Register'!$G$2:$G$29,"Low")
A5: Explainability / transparency | B5: =COUNTIF('Risk Register'!$C$2:$C$29,A5) | C5: =COUNTIFS('Risk Register'!$C$2:$C$29,$A5,'Risk Register'!$G$2:$G$29,"High") | D5: =COUNTIFS('Risk Register'!$C$2:$C$29,$A5,'Risk Register'!$G$2:$G$29,"Medium") | E5: =COUNTIFS('Risk Register'!$C$2:$C$29,$A5,'Risk Register'!$G$2:$G$29,"Low")
A6: Consistency / determinism | B6: =COUNTIF('Risk Register'!$C$2:$C$29,A6) | C6: =COUNTIFS('Risk Register'!$C$2:$C$29,$A6,'Risk Register'!$G$2:$G$29,"High") | D6: =COUNTIFS('Risk Register'!$C$2:$C$29,$A6,'Risk Register'!$G$2:$G$29,"Medium") | E6: =COUNTIFS('Risk Register'!$C$2:$C$29,$A6,'Risk Register'!$G$2:$G$29,"Low")
A7: Data quality | B7: =COUNTIF('Risk Register'!$C$2:$C$29,A7) | C7: =COUNTIFS('Risk Register'!$C$2:$C$29,$A7,'Risk Register'!$G$2:$G$29,"High") | D7: =COUNTIFS('Risk Register'!$C$2:$C$29,$A7,'Risk Register'!$G$2:$G$29,"Medium") | E7: =COUNTIFS('Risk Register'!$C$2:$C$29,$A7,'Risk Register'!$G$2:$G$29,"Low")
A8: Human oversight | B8: =COUNTIF('Risk Register'!$C$2:$C$29,A8) | C8: =COUNTIFS('Risk Register'!$C$2:$C$29,$A8,'Risk Register'!$G$2:$G$29,"High") | D8: =COUNTIFS('Risk Register'!$C$2:$C$29,$A8,'Risk Register'!$G$2:$G$29,"Medium") | E8: =COUNTIFS('Risk Register'!$C$2:$C$29,$A8,'Risk Register'!$G$2:$G$29,"Low")
A9: Security | B9: =COUNTIF('Risk Register'!$C$2:$C$29,A9) | C9: =COUNTIFS('Risk Register'!$C$2:$C$29,$A9,'Risk Register'!$G$2:$G$29,"High") | D9: =COUNTIFS('Risk Register'!$C$2:$C$29,$A9,'Risk Register'!$G$2:$G$29,"Medium") | E9: =COUNTIFS('Risk Register'!$C$2:$C$29,$A9,'Risk Register'!$G$2:$G$29,"Low")
A10: Privacy | B10: =COUNTIF('Risk Register'!$C$2:$C$29,A10) | C10: =COUNTIFS('Risk Register'!$C$2:$C$29,$A10,'Risk Register'!$G$2:$G$29,"High") | D10: =COUNTIFS('Risk Register'!$C$2:$C$29,$A10,'Risk Register'!$G$2:$G$29,"Medium") | E10: =COUNTIFS('Risk Register'!$C$2:$C$29,$A10,'Risk Register'!$G$2:$G$29,"Low")
A11: Change management | B11: =COUNTIF('Risk Register'!$C$2:$C$29,A11) | C11: =COUNTIFS('Risk Register'!$C$2:$C$29,$A11,'Risk Register'!$G$2:$G$29,"High") | D11: =COUNTIFS('Risk Register'!$C$2:$C$29,$A11,'Risk Register'!$G$2:$G$29,"Medium") | E11: =COUNTIFS('Risk Register'!$C$2:$C$29,$A11,'Risk Register'!$G$2:$G$29,"Low")
A12: Third party | B12: =COUNTIF('Risk Register'!$C$2:$C$29,A12) | C12: =COUNTIFS('Risk Register'!$C$2:$C$29,$A12,'Risk Register'!$G$2:$G$29,"High") | D12: =COUNTIFS('Risk Register'!$C$2:$C$29,$A12,'Risk Register'!$G$2:$G$29,"Medium") | E12: =COUNTIFS('Risk Register'!$C$2:$C$29,$A12,'Risk Register'!$G$2:$G$29,"Low")
A13: Monitoring | B13: =COUNTIF('Risk Register'!$C$2:$C$29,A13) | C13: =COUNTIFS('Risk Register'!$C$2:$C$29,$A13,'Risk Register'!$G$2:$G$29,"High") | D13: =COUNTIFS('Risk Register'!$C$2:$C$29,$A13,'Risk Register'!$G$2:$G$29,"Medium") | E13: =COUNTIFS('Risk Register'!$C$2:$C$29,$A13,'Risk Register'!$G$2:$G$29,"Low")
A14: Governance | B14: =COUNTIF('Risk Register'!$C$2:$C$29,A14) | C14: =COUNTIFS('Risk Register'!$C$2:$C$29,$A14,'Risk Register'!$G$2:$G$29,"High") | D14: =COUNTIFS('Risk Register'!$C$2:$C$29,$A14,'Risk Register'!$G$2:$G$29,"Medium") | E14: =COUNTIFS('Risk Register'!$C$2:$C$29,$A14,'Risk Register'!$G$2:$G$29,"Low")
A15: Total | B15: =SUM(B4:B14) | C15: =SUM(C4:C14) | D15: =SUM(D4:D14) | E15: =SUM(E4:E14)
A17: Check: total risks equals rows on register | B17: =IF(B15=COUNTA('Risk Register'!$A$2:$A$29),"OK","MISMATCH")

Sheet Scoring
A1: Scoring scales and rating bands
A3: Score | B3: Likelihood (1-5) | C3: Impact (1-5)
A4: 1 | B4: Rare: would need unusual circumstances | C4: Negligible: cosmetic, no effect on reconciliation outcome
A5: 2 | B5: Unlikely | C5: Minor: extra review time; result still correct
A6: 3 | B6: Possible | C6: Moderate: some errors or misleading output; detectable on review
A7: 4 | B7: Likely | C7: Major: material error missed or wrong output relied on
A8: 5 | B8: Almost certain / already true | C8: Severe: misstatement, unauthorised change to ledger, or data breach
A10: Rating bands (edit the blue cells to change bands; ratings on the Risk Register recalculate)
A11: High if inherent score at or above | B11: 15
A12: Medium if inherent score at or above | B12: 8
A14: Assumptions: scores are the reviewer's judgement (self-assessment), inherent (before any control), and are reviewed in Phase 3 once controls are mapped. Bands are a review convention, not a standard.
A16: Framework references: NIST AI RMF 1.0 subcategory numbers and ISO/IEC 42001 Annex A are cited at area level from the reviewer's knowledge and must be checked against the source documents before the report is issued.

Sheet Not applicable (no LLM)
A1: Risks considered and recorded as not applicable at the pinned commit (no LLM is called). Reassess if an LLM layer is added.
A3: Risk | B3: Why not applicable | C3: Reference
A4: Prompt injection via transaction descriptions | B4: No prompt is built and no model reads ledger text. (Free-text fields are only compared or displayed.) | C4: OWASP LLM01
A5: Hallucinated or unsupported explanations | B5: Variance text is generated by string templates over SQL results. | C5: OWASP LLM09; NIST MEASURE 2.5
A6: Non-deterministic output between runs | B6: Rules are deterministic; replaced by a determinism test in Phase 4 (see ToR). | C6: NIST MEASURE 2.5
A7: Personal data sent to an LLM provider; retention and training terms | B7: No LLM provider receives data. Data still leaves to Xero/Intuit (in scope) and public GitHub/Streamlit (R19). | C7: OWASP LLM02; NIST MEASURE 2.10
A8: Silent model version change by provider | B8: No model. Dependency drift is covered by R11. | C8: NIST MANAGE 2.3
A9: Model and prompt inventory | B9: Nothing to inventory beyond the code and dependencies. | C9: NIST GOVERN 1.6; ISO 42001 A.6
