Workbook

Sheet Summary
A1: Control assessment summary (Phase 3, design only)
A3: Controls identified | B3: =COUNTA('Control Matrix'!$A$2:$A$30)
A4: In place (Y) | B4: =COUNTIF('Control Matrix'!$F$2:$F$30,"Y")
A5: Partial | B5: =COUNTIF('Control Matrix'!$F$2:$F$30,"Partial")
A6: Not in place (N) | B6: =COUNTIF('Control Matrix'!$F$2:$F$30,"N")
A7: Risks total | B7: =COUNTA('Risk Coverage'!$A$5:$A$32)
A8: High risks | B8: =COUNTIF('Risk Coverage'!$C$5:$C$32,"High")
A9: High risks with status GAP | B9: =COUNTIFS('Risk Coverage'!$C$5:$C$32,"High",'Risk Coverage'!$H$5:$H$32,"GAP*")
A10: High risks Partly covered or Covered | B10: =COUNTIFS('Risk Coverage'!$C$5:$C$32,"High",'Risk Coverage'!$H$5:$H$32,"<>GAP*")
A11: All risks with status GAP | B11: =COUNTIF('Risk Coverage'!$H$5:$H$32,"GAP*")
A12: Risks with no control identified | B12: =COUNTIF('Risk Coverage'!$H$5:$H$32,"GAP: no control identified")
A14: Completion test (Phase 3): every High risk is linked to a control or marked GAP. | B14: =IF(COUNTIFS('Risk Coverage'!$C$5:$C$32,"High",'Risk Coverage'!$D$5:$D$32,0,'Risk Coverage'!$H$5:$H$32,"<>GAP*")=0,"OK","CHECK")
A16: Method: controls in place were identified from the code and documents at the pinned commit. Controls not in place are recorded as gaps and were NOT added before testing; they become findings in Phase 5 and are retested after remediation. Design results are the reviewer's assessment; operating effectiveness is tested in Phase 4. C17 (the independent test set) is a review procedure, not a management control, until adopted by the owner.
A18: Phase 4 update (23 Sep 2026): the Operating result column records tests of operating effectiveness performed from the pinned code and committed data (evidence log E-01 to E-05). 'Not in place (confirmed)' means the absence was checked, not assumed. C12 could not be tested; C29 awaits the challenge review.

Sheet Control Matrix
A1: Control ID | B1: Risk(s) addressed | C1: Description | D1: Preventive / detective | E1: Manual / automated | F1: In place? (Y/N/Partial) | G1: Test of design | H1: Test of operating effectiveness (planned) | I1: Evidence ref | J1: Design result (Phase 3) | K1: Operating result (Phase 4)
A2: C01 | B2: None (Xero side; no separate register risk) | C2: Xero connector requests only read scopes (granular *.read) | D2: Preventive | E2: Automated | F2: Y | G2: Inspect SCOPE constant and OAuth POSTs: confirm no write scopes and no write calls. | H2: Confirm granted scopes in the Xero developer portal/app connection and grep all requests calls for non-GET (other than token POST). | I2: xero_connector.py:18-28, 75, 91; Evidence log E-04 | J2: Adequate | K2: Effective (code and requested scope); portal grant not verified
A3: C02 | B3: R16 | C3: QuickBooks connector code issues only GET queries and token POSTs | D3: Preventive | E3: Automated | F3: Partial | G3: Inspect code: confirm no write calls. Design limitation: control depends on code, not on the permission granted. | H3: Grep all requests calls; confirm no POST except token endpoints. Compare requested scope with the minimum needed. | I3: quickbooks_connector.py:24, 73, 90, 110, 132; Evidence log E-04 | J3: Partly adequate | K3: Operates as described; design limit remains (scope is read/write)
A4: C03 | B4: R16 | C4: QuickBooks scope restricted to the minimum (read-only) so the platform enforces read-only | D4: Preventive | E4: Automated | F4: N | G4: Would be adequate if scope were read-only. Intuit's accounting scope grants read/write. | H4: Not in place. Retest after remediation. | I4: quickbooks_connector.py:24; Evidence log E-04 | J4: Not in place | K4: Not in place (confirmed)
A5: C04 | B5: R18 | C5: Secrets held in a git-ignored .env; .env.example committed with blanks only | D5: Preventive | E5: Manual | F5: Y | G5: Inspect .gitignore and .env.example; confirm no values. | H5: git log --all -- .env (expect empty); inspect committed files for credential patterns. | I5: Northbridge .gitignore; .env.example; Evidence log E-04 | J5: Adequate (single layer) | K5: Effective
A6: C05 | B6: R17 | C6: Refresh tokens stored in a secrets manager or encrypted, not plaintext | D6: Preventive | E6: Automated | F6: N | G6: Not in place: save_tokens writes plaintext to .env. | H6: Not in place. Retest after remediation. | I6: xero_connector.py:190-193; Evidence log E-04 | J6: Not in place | K6: Not in place (confirmed: plaintext via set_key)
A7: C06 | B7: R18 | C7: Repeatable secrets scan before publishing to the public repo | D7: Detective | E7: Manual | F7: Partial | G7: Build notes report a scan (Session 6); not automated or repeated. | H7: Run a secrets scanner over the full git history at the pinned commit; record output. | I7: northbridge-ledger-agent-plan.md (Session 6); Evidence log E-04, E-06 | J7: Partly adequate | K7: No matches for credential patterns in code files across all history (regex search; md, csv, db excluded; no scanner run); one-off by reviewer, not repeatable by owner
A8: C07 | B8: R19 | C8: Project restricted to fictional and vendor sandbox data; data labelled synthetic where shown | D8: Preventive | E8: Manual | F8: Y | G8: Inspect README scope statement and dashboard banner. | H8: Confirm the committed databases contain no real client data (sample review of contacts); confirm synthetic banner displays. | I8: README.md:7, 122; app.py:132-138; Evidence log E-04, E-06 | J8: Adequate | K8: Partly evidenced: sampled first 12 contact names per database only; committed names appear fictional, seeded or Intuit sandbox (QuickBooks demo has address-like names); real brand names in Xero demo; personal data not ruled out
A9: C08 | B9: R19 | C9: Data-protection assessment and data handling rules before any real data is used | D9: Preventive | E9: Manual | F9: N | G9: No documented procedure. Policy is a rule in the build plan only. | H9: Not in place. | I9: northbridge-ledger-agent-plan.md; Evidence log E-04 | J9: Not in place | K9: Not in place (confirmed)
A10: C09 | B10: R03; R15; R25; R28 | C10: README and dashboard disclose limitations (independent project, synthetic scale test not an accuracy claim, fictional data) | D10: Preventive | E10: Manual | F10: Partial | G10: Inspect wording for what it states and what it omits (intended use, known limits on real books, owner). | H10: Compare disclosures with measured results; confirm the caption on the public dashboard matches the README. | I10: README.md:96-101, 122; app.py:132-138; Evidence log E-04 | J10: Partly adequate | K10: Partly effective: omits intended use, limits on real books, false negatives, production status
A11: C10 | B11: R25 | C11: Documented owner, intended use, users of output, known limitations and escalation route | D11: Preventive | E11: Manual | F11: N | G11: Owner is implicit (sole developer); no intended-use statement. | H11: Not in place. | I11: Evidence log E-04 | J11: Not in place | K11: Not in place (confirmed)
A12: C11 | B12: R12; R13 | C12: Data coverage table shows rows loaded per table and data-quality counts (unlinked payments, no-contact lines, voided invoices) | D12: Detective | E12: Automated | F12: Partial | G12: Inspect compute_data_stats: shows counts but has no thresholds and no comparison to source totals. | H12: Re-perform the counts from the database for each dataset; compare with dashboard values. | I12: src/reconciliation/stats.py; app.py:48-68; Evidence log E-04, E-06 | J12: Partly adequate | K12: Operates: dashboard counts equal recount on the same database (arithmetic consistency); not evidence of pull completeness against source totals; no thresholds
... A30: C29 | B30: R28 | C30: Independence disclosure in ToR and a challenge review of testing | D30: Detective | E30: Manual | F30: Partial | G30: Disclosure in place (ToR s1); challenge review planned for Phase 4, not yet done. | H30: Perform the challenge review in Phase 4 and record challenges. | I30: terms_of_reference.md s1 | J30: Partly adequate | K30: Not yet tested (challenge review pending)

Sheet Risk Coverage
A1: Risk-to-control coverage (counts recalculate from the Control Matrix)
A2: Risk ID, description and rating are copied from 02_risk/risk_register.xlsx as at 23 Sep 2026, updated after the Phase 4 challenge review (R08 now High; R10 rescored, still Medium). Static; refresh if scores change.
A4: Risk ID | B4: Description | C4: Rating | D4: Controls linked | E4: Controls in place (Y) | F4: Controls partial | G4: Controls not in place (N) | H4: Coverage status
A5: R01 | B5: Real errors missed on data unlike the planted patterns (false negatives) | C5: High | D5: =COUNTIF('Control Matrix'!$B$2:$B$30,"*"&A5&"*") | E5: =COUNTIFS('Control Matrix'!$B$2:$B$30,"*"&$A5&"*",'Control Matrix'!$F$2:$F$30,"Y") | F5: =COUNTIFS('Control Matrix'!$B$2:$B$30,"*"&$A5&"*",'Control Matrix'!$F$2:$F$30,"Partial") | G5: =COUNTIFS('Control Matrix'!$B$2:$B$30,"*"&$A5&"*",'Control Matrix'!$F$2:$F$30,"N") | H5: =IF(D5=0,"GAP: no control identified",IF(E5>0,"Covered",IF(F5>0,"Partly covered","GAP: control not in place")))
A6: R02 | B6: Clean items wrongly flagged (false positives) create review burden and desensitise reviewers | C6: Medium | D6: =COUNTIF('Control Matrix'!$B$2:$B$30,"*"&A6&"*") | E6: =COUNTIFS('Control Matrix'!$B$2:$B$30,"*"&$A6&"*",'Control Matrix'!$F$2:$F$30,"Y") | F6: =COUNTIFS('Control Matrix'!$B$2:$B$30,"*"&$A6&"*",'Control Matrix'!$F$2:$F$30,"Partial") | G6: =COUNTIFS('Control Matrix'!$B$2:$B$30,"*"&$A6&"*",'Control Matrix'!$F$2:$F$30,"N") | H6: =IF(D6=0,"GAP: no control identified",IF(E6>0,"Covered",IF(F6>0,"Partly covered","GAP: control not in place")))
A7: R03 | B7: Reported accuracy is overstated because validation was circular (planted anomalies designed to fit the rules) | C7: High | D7: =COUNTIF('Control Matrix'!$B$2:$B$30,"*"&A7&"*") | E7: =COUNTIFS('Control Matrix'!$B$2:$B$30,"*"&$A7&"*",'Control Matrix'!$F$2:$F$30,"Y") | F7: =COUNTIFS('Control Matrix'!$B$2:$B$30,"*"&$A7&"*",'Control Matrix'!$F$2:$F$30,"Partial") | G7: =COUNTIFS('Control Matrix'!$B$2:$B$30,"*"&$A7&"*",'Control Matrix'!$F$2:$F$30,"N") | H7: =IF(D7=0,"GAP: no control identified",IF(E7>0,"Covered",IF(F7>0,"Partly covered","GAP: control not in place")))
A8: R04 | B8: Duplicate supplier bills not detected: A1 checks sales invoices (ACCREC) only | C8: Medium | D8: =COUNTIF('Control Matrix'!$B$2:$B$30,"*"&A8&"*") | E8: =COUNTIFS('Control Matrix'!$B$2:$B$30,"*"&$A8&"*",'Control Matrix'!$F$2:$F$30,"Y") | F8: =COUNTIFS('Control Matrix'!$B$2:$B$30,"*"&$A8&"*",'Control Matrix'!$F$2:$F$30,"Partial") | G8: =COUNTIFS('Control Matrix'!$B$2:$B$30,"*"&$A8&"*",'Control Matrix'!$F$2:$F$30,"N") | H8: =IF(D8=0,"GAP: no control identified",IF(E8>0,"Covered",IF(F8>0,"Partly covered","GAP: control not in place")))
A9: R05 | B9: A1 compares adjacent sorted rows only, so three or more near-identical entries may be under-reported | C9: Low | D9: =COUNTIF('Control Matrix'!$B$2:$B$30,"*"&A9&"*") | E9: =COUNTIFS('Control Matrix'!$B$2:$B$30,"*"&$A9&"*",'Control Matrix'!$F$2:$F$30,"Y") | F9: =COUNTIFS('Control Matrix'!$B$2:$B$30,"*"&$A9&"*",'Control Matrix'!$F$2:$F$30,"Partial") | G9: =COUNTIFS('Control Matrix'!$B$2:$B$30,"*"&$A9&"*",'Control Matrix'!$F$2:$F$30,"N") | H9: =IF(D9=0,"GAP: no control identified",IF(E9>0,"Covered",IF(F9>0,"Partly covered","GAP: control not in place")))
A10: R06 | B10: Fixed thresholds and tolerances (A3 £500, match tolerances, windows) are uncalibrated, unapproved and easy to avoid | C10: Medium | D10: =COUNTIF('Control Matrix'!$B$2:$B$30,"*"&A10&"*") | E10: =COUNTIFS('Control Matrix'!$B$2:$B$30,"*"&$A10&"*",'Control Matrix'!$F$2:$F$30,"Y") | F10: =COUNTIFS('Control Matrix'!$B$2:$B$30,"*"&$A10&"*",'Control Matrix'!$F$2:$F$30,"Partial") | G10: =COUNTIFS('Control Matrix'!$B$2:$B$30,"*"&$A10&"*",'Control Matrix'!$F$2:$F$30,"N") | H10: =IF(D10=0,"GAP: no control identified",IF(E10>0,"Covered",IF(F10>0,"Partly covered","GAP: control not in place")))
A11: R07 | B11: Statistical outlier check (A7) is unreliable on small or uniform account populations | C11: Medium | D11: =COUNTIF('Control Matrix'!$B$2:$B$30,"*"&A11&"*") | E11: =COUNTIFS('Control Matrix'!$B$2:$B$30,"*"&$A11&"*",'Control Matrix'!$F$2:$F$30,"Y") | F11: =COUNTIFS('Control Matrix'!$B$2:$B$30,"*"&$A11&"*",'Control Matrix'!$F$2:$F$30,"Partial") | G11: =COUNTIFS('Control Matrix'!$B$2:$B$30,"*"&$A11&"*",'Control Matrix'!$F$2:$F$30,"N") | H11: =IF(D11=0,"GAP: no control identified",IF(E11>0,"Covered",IF(F11>0,"Partly covered","GAP: control not in place")))
A12: R08 | B12: Reconciliation attributes bank lines to the wrong document, loses genuine matches or gives different results depending on record order (first match taken, no one-to-one allocation) | C12: High | D12: =COUNTIF('Control Matrix'!$B$2:$B$30,"*"&A12&"*") | E12: =COUNTIFS('Control Matrix'!$B$2:$B$30,"*"&$A12&"*",'Control Matrix'!$F$2:$F$30,"Y") | F12: =COUNTIFS('Control Matrix'!$B$2:$B$30,"*"&$A12&"*",'Control Matrix'!$F$2:$F$30,"Partial") | G12: =COUNTIFS('Control Matrix'!$B$2:$B$30,"*"&$A12&"*",'Control Matrix'!$F$2:$F$30,"N") | H12: =IF(D12=0,"GAP: no control identified",IF(E12>0,"Covered",IF(F12>0,"Partly covered","GAP: control not in place")))
A13: R09 | B13: Weekend-posting rule (A4) produces false positives on legitimate items and ignores public holidays | C13: Low | D13: =COUNTIF('Control Matrix'!$B$2:$B$30,"*"&A13&"*") | E13: =COUNTIFS('Control Matrix'!$B$2:$B$30,"*"&$A13&"*",'Control Matrix'!$F$2:$F$30,"Y") | F13: =COUNTIFS('Control Matrix'!$B$2:$B$30,"*"&$A13&"*",'Control Matrix'!$F$2:$F$30,"Partial") | G13: =COUNTIFS('Control Matrix'!$B$2:$B$30,"*"&$A13&"*",'Control Matrix'!$F$2:$F$30,"N") | H13: =IF(D13=0,"GAP: no control identified",IF(E13>0,"Covered",IF(F13>0,"Partly covered","GAP: control not in place")))
A14: R10 | B14: Variance explanations name top contacts but not causes, and may be read as a causal explanation | C14: Medium | D14: =COUNTIF('Control Matrix'!$B$2:$B$30,"*"&A14&"*") | E14: =COUNTIFS('Control Matrix'!$B$2:$B$30,"*"&$A14&"*",'Control Matrix'!$F$2:$F$30,"Y") | F14: =COUNTIFS('Control Matrix'!$B$2:$B$30,"*"&$A14&"*",'Control Matrix'!$F$2:$F$30,"Partial") | G14: =COUNTIFS('Control Matrix'!$B$2:$B$30,"*"&$A14&"*",'Control Matrix'!$F$2:$F$30,"N") | H14: =IF(D14=0,"GAP: no control identified",IF(E14>0,"Covered",IF(F14>0,"Partly covered","GAP: control not in place")))
A15: R11 | B15: Unpinned dependencies allow silent behaviour change across installs or redeploys | C15: Medium | D15: =COUNTIF('Control Matrix'!$B$2:$B$30,"*"&A15&"*") | E15: =COUNTIFS('Control Matrix'!$B$2:$B$30,"*"&$A15&"*",'Control Matrix'!$F$2:$F$30,"Y") | F15: =COUNTIFS('Control Matrix'!$B$2:$B$30,"*"&$A15&"*",'Control Matrix'!$F$2:$F$30,"Partial") | G15: =COUNTIFS('Control Matrix'!$B$2:$B$30,"*"&$A15&"*",'Control Matrix'!$F$2:$F$30,"N") | H15: =IF(D15=0,"GAP: no control identified",IF(E15>0,"Covered",IF(F15>0,"Partly covered","GAP: control not in place")))
A16: R12 | B16: Incomplete or malformed ledger data (missing contacts, voided invoices, unlinked payments) yields confident but wrong results | C16: Medium | D16: =COUNTIF('Control Matrix'!$B$2:$B$30,"*"&A16&"*") | E16: =COUNTIFS('Control Matrix'!$B$2:$B$30,"*"&$A16&"*",'Control Matrix'!$F$2:$F$30,"Y") | F16: =COUNTIFS('Control Matrix'!$B$2:$B$30,"*"&$A16&"*",'Control Matrix'!$F$2:$F$30,"Partial") | G16: =COUNTIFS('Control Matrix'!$B$2:$B$30,"*"&$A16&"*",'Control Matrix'!$F$2:$F$30,"N") | H16: =IF(D16=0,"GAP: no control identified",IF(E16>0,"Covered",IF(F16>0,"Partly covered","GAP: control not in place")))
... A32: R28 | B32: Reviewer is also the developer, and code was built with AI coding tools, weakening independence and provenance assurance | C32: Medium | D32: =COUNTIF('Control Matrix'!$B$2:$B$30,"*"&A32&"*") | E32: =COUNTIFS('Control Matrix'!$B$2:$B$30,"*"&$A32&"*",'Control Matrix'!$F$2:$F$30,"Y") | F32: =COUNTIFS('Control Matrix'!$B$2:$B$30,"*"&$A32&"*",'Control Matrix'!$F$2:$F$30,"Partial") | G32: =COUNTIFS('Control Matrix'!$B$2:$B$30,"*"&$A32&"*",'Control Matrix'!$F$2:$F$30,"N") | H32: =IF(D32=0,"GAP: no control identified",IF(E32>0,"Covered",IF(F32>0,"Partly covered","GAP: control not in place")))
